gradio_variableslider/__init__.py
gradio_variableslider/variableslider.py
gradio_variableslider/variableslider.pyi
gradio_variableslider/templates/component/index.js
gradio_variableslider/templates/component/style.css
gradio_variableslider/templates/example/index.js
gradio_variableslider/templates/example/style.css
gradio_variableslider-0.0.5.dist-info/METADATA
gradio_variableslider-0.0.5.dist-info/WHEEL
gradio_variableslider-0.0.5.dist-info/RECORD
