Metadata-Version: 2.3
Name: gradio_variableslider
Version: 0.0.5
Summary: Python library for easily interacting with trained machine learning models
Author-email: Keiane Balicanta <balica15@students.rowan.edu>
License-Expression: Apache-2.0
Keywords: gradio-custom-component,gradio-custom-slider,gradio-float-values,gradio-template-Slider
Classifier: Development Status :: 3 - Alpha
Classifier: License :: OSI Approved :: Apache Software License
Classifier: Operating System :: OS Independent
Classifier: Programming Language :: Python :: 3
Classifier: Programming Language :: Python :: 3 :: Only
Classifier: Programming Language :: Python :: 3.8
Classifier: Programming Language :: Python :: 3.9
Classifier: Programming Language :: Python :: 3.10
Classifier: Programming Language :: Python :: 3.11
Classifier: Topic :: Scientific/Engineering
Classifier: Topic :: Scientific/Engineering :: Artificial Intelligence
Classifier: Topic :: Scientific/Engineering :: Visualization
Requires-Python: >=3.8
Requires-Dist: gradio<5.0,>=4.0
Provides-Extra: dev
Requires-Dist: build; extra == 'dev'
Requires-Dist: twine; extra == 'dev'
